onf_rtm/__init__.py
onf_rtm/misc.py
onf_rtm-1.0.1.dist-info/METADATA
onf_rtm-1.0.1.dist-info/WHEEL
onf_rtm-1.0.1.dist-info/RECORD
