Metadata-Version: 2.1
Name: onf-rtm
Version: 1.0.1
Summary: 
License: GNU GPLv3
Author: ONF-RTM
Author-email: clement.roussel@onf.fr
Requires-Python: >=3.9,<4.0
Classifier: License :: Other/Proprietary License
Classifier: Programming Language :: Python :: 3
Classifier: Programming Language :: Python :: 3.9
Classifier: Programming Language :: Python :: 3.10
Classifier: Programming Language :: Python :: 3.11
Requires-Dist: matplotlib (>=3.6.2,<4.0.0)
Requires-Dist: numpy (>=1.24.1,<2.0.0)
Requires-Dist: pandas (>=1.5.2,<2.0.0)
Requires-Dist: pyshp (>=2.3.1,<3.0.0)
Requires-Dist: rdp (>=0.8,<0.9)
Requires-Dist: scipy (>=1.9.3,<2.0.0)
Requires-Dist: simpledbf (>=0.2.6,<0.3.0)
Requires-Dist: visvalingamwyatt (>=0.2.0,<0.3.0)
